{"version":1,"meta":{"name":"danger","fps":30,"columns":45,"rows":20,"frameCount":43,"colored":false,"generatedWith":{"thresholdLow":5,"thresholdHigh":235,"chars":" .~-_=+*%#0oOxX@$","fontRatio":0.44}},"frames":[["                                             ","                                             ","                                             ","                                             ","                                             ","                                             ","                                             ","                                             ","                                             ","                                             ","                                             ","                                             ","                                             ","                                             ","                                        0_%  ","                                        .    ","                                            %","                                        O   @","                              -            @ ","                              0_______=*O    "],["                                             ","                                             ","                                             ","                                             ","                                             ","                                             ","                                             ","                                             ","                                             ","                                             ","                                    **       ","                                   o   x     ","                                    X   0    ","                                         +   ","                                          ~  ","                                        .    ","                                            %","                                        O   @","                                  O        @ ","                                   =___*O    "],["                                             ","                                             ","                                             ","                                             ","                                             ","                                             ","                                             ","                                             ","                                             ","                                             ","                                    *+       ","                                   o   x     ","                                    X   0    ","                                         +   ","                                          ~  ","                                        .    ","                                            %","                                        O   @","                                  O        @ ","                                   =___*O    "],["                                             ","                         _.=                 ","                         -                   ","                          +                  ","                           0   X             ","                            x   0            ","                                 +           ","                                  -          ","                                             ","                                 -           ","                                  *          ","                                   o   x     ","                                    X   0    ","                                         +   ","                                          ~  ","                                        .    ","                                            o","                                             ","                                             ","                                             "],["                   @#_-_*x                   ","                 #         _                 ","                -        ~                   ","               ~          +                  ","                           0   X             ","                            x   0            ","                                 +           ","                                  -          ","                                             ","                                 -           ","                                  *          ","                                   o   x     ","                                    X   0    ","                                         +   ","                                       ~ _   ","                                             ","                                             ","                                             ","                                             ","                                             "],["                   @#_-_*x                   ","                 #         _                 ","                -        ~                   ","                          +                  ","                 _         0   X             ","            @   %           x   0            ","           O   O                 +           ","          %   @                   -          ","         _                                   ","         @+%                     -           ","                                  *          ","                                   o   @     ","                                     ox      ","                                             ","                                             ","                                             ","                                             ","                                             ","                                             ","                                             "],["                   @#_-_*x                   ","                 #         _                 ","                -        ~                   ","                          +                  ","                 _         0   X             ","            @   %           x   0            ","           O   O                 +           ","          %   @                   -          ","         _                                   ","        .                        _  o        ","          ~                                  ","         +                                   ","    X   0                                    ","   0   X                                     ","                                             ","                                             ","                                             ","                                             ","                                             ","                                             "],["                   @#_-_*x                   ","                 #         _                 ","                -        ~                   ","                          +                  ","                 _         0   X             ","            @   %           x   0            ","           O   O                 *           ","          %   @                ##            ","         _                                   ","        .                                    ","          ~                                  ","         +                                   ","    X   0                                    ","   0   X                                     ","  +                                          "," ~                                           ","x                                            ","    #                                        ","  .     .                                    ","    O*=_*                                    "],["                   @#_-_*x                   ","                 #         _                 ","                -        ~                   ","                          +                  ","                 _         0  .              ","            @   %                            ","           O   O                             ","          %   @                              ","         _                                   ","        .                                    ","          ~                                  ","         +                                   ","    X   0                                    ","   0   X                                     ","  +                                          "," ~                                           ","x                                            ","    #                                        ","  .                    x                     ","    O*=_______________+                      "],["                   @#_-_*x                   ","                 #         _                 ","                -        %=O                 ","                                             ","                 _                           ","            @   %                            ","           O   O                             ","          %   @                              ","         _                                   ","        .                                    ","          ~                                  ","         +                                   ","    X   0                                    ","   0   X                                     ","  +                                          "," ~                                           ","x                                            ","    #                                        ","  .                                  X       ","    O*=_____________________________+        "],["                   @#0                       ","                 #    o                      ","                -                            ","                                             ","                 _                           ","            @   %                            ","           O   O                             ","          %   @       oX                     ","         _                                   ","        .                                    ","          ~                                  ","         +                                   ","    X   0                                    ","   0   X                                     ","  +                                     X+0  "," ~                                      .    ","x                                           %","    #                                   O   @","  .                                        @ ","    O*=________________________________*O    "],["                                             ","                                             ","                0+x                          ","                                             ","                 _                           ","            @   %                            ","           O   O                             ","          %   @       oX                     ","         _                                   ","        .            O+0          x-=        ","          ~                       *          ","         +                         o   x     ","    X   0                           X   0    ","   0   X                                 +   ","  +                                       ~  "," ~                                      .    ","x                                           %","    #                                   O   @","  .                                        @ ","    O*=________________________________*O    "],["                                             ","                                             ","                                             ","                                             ","              oO             x0              ","            @   #           @   0            ","           O   O                 *           ","          %   @       oX          -          ","         _                                   ","        .                        -           ","          ~                       *          ","         +                         o   x     ","    X   0                           X   0    ","   0   X                                 +   ","  +                                       ~  "," ~                                      .    ","x                                           %","    #                                   O   @","  .                                        @ ","    O*=________________________________*O    "],["                       o%x                   ","                      @    _                 ","                         ~                   ","                          +                  ","                           0   X             ","                            x   0            ","           @#x                   *           ","          %           oX          -          ","         _                                   ","        .                        -           ","          ~          *.=          *          ","         +                         o   x     ","    X   0                           X   0    ","   0   X                                 +   ","  +                                       ~  "," ~                                      .    ","x                                           %","    #                                   O   @","  .                                        @ ","    O*=________________________________*O    "],["                   @%_-_*x                   ","                 #         _                 ","                -        ~                   ","               =  .       +                  ","                           0   X             ","                            x   0            ","                                 *           ","                      oX          -          ","         *._                                 ","        .                        -           ","          ~                       *          ","         +            x            o   x     ","    X   0                           X   0    ","   0   X                                 +   ","  +                                       ~  "," ~                                      .    ","x                                           %","    #                                   O   @","  .                                        @ ","    O*=________________________________*O    "],["                   @%_-_*x                   ","                 #         _                 ","                -        ~                   ","                          +                  ","                 _         0   X             ","            @   %           x   0            ","           O   O                 *           ","            *+        oX          -          ","                                             ","                                 -           ","          #                       *          ","         +           ~ .           o   x     ","    X   0                           X   0    ","   0   X                                 +   ","  +                                       ~  "," ~                                      .    ","x                                           %","    #                                   O   @","  .                                        @ ","    O*=________________________________*O    "],["                   @%_-_*x                   ","                 #         _                 ","                -        ~                   ","                          +                  ","                 _         0   X             ","            @   %           x   0            ","           O   O                 *           ","          %   @       oX          -          ","         _                                   ","        ~                        -           ","         XX                       *          ","                                   o   x     ","    X   0             @             X   0    ","   0   X                                 +   ","  +                                       ~  "," ~                                      .    ","x                                           %","    #                                   O   @","  .                                        @ ","    O*=________________________________*O    "],["                   @%_-_*x                   ","                 #         _                 ","                -        ~                   ","                          +                  ","                 _         0   X             ","            @   %           x   0            ","           O   O                 *           ","          %   @       oX          -          ","         _                                   ","        .                        -           ","          ~                       *          ","         +                         o   x     ","    X   @             o@            X   0    ","   0   X                                 +   ","  +                                       ~  "," ~                                      .    ","x                                           %","    #                                   O   @","  .                                        @ ","    O*=________________________________*O    "],["                   @%_-_*x                   ","                 #         _                 ","                -        ~                   ","                          +                  ","                 _         0   X             ","            @   %           x   0            ","           O   O                 *           ","          %   @       oX          -          ","         _                                   ","        .                        -           ","          ~                       *          ","         +                         o   x     ","    X   0             o@            X   0    ","   0   X                                 +   ","  +                                       ~  "," ~                                      .    ","x                                           %","    #                                   O   @","  .                                        @ ","    O*=________________________________*O    "],["                   @%_-_*x                   ","                 #         _                 ","                -        ~                   ","                          +                  ","                 _         0   X             ","            @   %           x   0            ","           O   O                 *           ","          %   @       oX          -          ","         _                                   ","        .                        -           ","          ~                       *          ","         +                         o   x     ","    X   0             o@            X   0    ","   0   X                                 +   ","  +                                       ~  "," ~                                      .    ","x                                           %","    #                                   O   @","  .                                        @ ","    O*=________________________________*O    "],["                   @%_-_*x                   ","                 #         _                 ","                -        ~                   ","                          +                  ","                 _         0   X             ","            @   %           x   0            ","           O   O                 *           ","          %   @       oX          -          ","         _                                   ","        .                        -           ","          ~                       *          ","         +                         o   x     ","    X   0             O             X   0    ","   0   X            @   O                +   ","  +                 o   %                 ~  "," ~                                      .    ","x                                           %","    #                                   O   @","  .                                        @ ","    O*=________________________________*O    "],["                   @%_-_*x                   ","                 #         _                 ","                -        ~                   ","                          +                  ","                 _         0   X             ","            @   %           x   0            ","           O   O                 *           ","          %   @       X           -          ","         _                                   ","        .                        -           ","          ~                       *          ","         +                         o   x     ","    X   0            x%O            X   0    ","   0   X            @   O                +   ","  +                 o   %                 ~  "," ~                                      .    ","x                                           %","    #                                   O   @","  .                                        @ ","    O*=________________________________*O    "],["                   @%_-_*x                   ","                 #         _                 ","                -        ~                   ","                          +                  ","                 _         0   X             ","            @   %           x   0            ","           O   O                 *           ","          %   @                   -          ","         _                                   ","        .                        -           ","          ~                       *          ","         +                         o   x     ","    X   0            +._            X   0    ","   0   X            @   O                +   ","  +                 o   %                 ~  "," ~                                      .    ","x                                           %","    #                                   O   @","  .                                        @ ","    O*=________________________________*O    "],["                   @%_-_*x                   ","                 #         _                 ","                -        ~                   ","                          +                  ","                 _         0   X             ","            @   %           x   0            ","           O   O                 *           ","          %   @                   -          ","         _                                   ","        .                        -           ","          ~                       *          ","         +                         o   x     ","    X   0            .              X   0    ","   0   X             %_*                 +   ","  +                 =   .                 ~  "," ~                    X                 .    ","x                                           %","    #                                   O   @","  .                                        @ ","    O*=________________________________*O    "],["                   @%_-_*x                   ","                 #         _                 ","                -        ~                   ","                          +                  ","                 _         0   X             ","            @   %           x   0            ","           O   O                 *           ","          %   @                   -          ","         _                                   ","        .                        -           ","          ~                       *          ","         +                         o   x     ","    X   0            = _            X   0    ","   0   X                                 +   ","  +                 %   _                 ~  "," ~                   - -@               .    ","x                                           %","    #                                   O   @","  .                                        @ ","    O*=________________________________*O    "],["                   @%_-_*x                   ","                 #         _                 ","                -        ~                   ","                          +                  ","                 _         0   X             ","            @   %           x   0            ","           O   O                 *           ","          %   @       X           -          ","         _                                   ","        .                        -           ","          ~                       *          ","         +                         o   x     ","    X   0            x*O            X   0    ","   0   X                                 +   ","  +                 X   O                 ~  "," ~                  O   #               .    ","x                                           %","    #                                   O   @","  .                                        @ ","    O*=________________________________*O    "],["                   @%_-_*x                   ","                 #         _                 ","                -        ~                   ","                          +                  ","                 _         0   X             ","            @   %           x   0            ","           O   O                 *           ","          %   @       oX          -          ","         _                                   ","        .                        -           ","          ~                       *          ","         +                         o   x     ","    X   0             o@            X   0    ","   0   X                                 +   ","  +                 %   _                 ~  "," ~                   - -@               .    ","x                                           %","    #                                   O   @","  .                                        @ ","    O*=________________________________*O    "],["                   @%_--*x                   ","                 #         _                 ","                -        ~                   ","                          +                  ","                 _         0   X             ","            @   %           x   0            ","           O   O                 *           ","          %   @       oX          -          ","         _                                   ","        .                        -           ","          ~                       *          ","         +                         o   x     ","    X   0             o@            X   0    ","   0   X             *-+                 +   ","  +                 =   .                 ~  "," ~                    X                 .    ","O                                           %","    #                                   O   @","  .                                        @ ","    x*=________________________________*O    "],["                   @%_--*x                   ","                 #         _                 ","                -        ~                   ","                          +                  ","                 _         0   X             ","            @   %           x   0            ","           O   O                 *           ","          %   @       oX          -          ","         _                                   ","        .                        -           ","          ~                       *          ","         +                         o   x     ","    X   0             O$            X   0    ","   0   X            @   O                +   ","  +                 o   %                 ~  "," ~                                      .    ","O                                           %","    #                                   O   @","  .                                        @ ","    x*=________________________________*O    "],["                   @%_--*x                   ","                 #         _                 ","                -        ~                   ","                          +                  ","                 _         0   X             ","            @   %           x   0            ","           O   O                 *           ","          %   @       oX          -          ","         _                                   ","        .                        -           ","          ~                       *          ","         +                         o   x     ","    X   0             O$            X   0    ","   0   X            @   O                +   ","  +                 o   %                 ~  "," ~                                      .    ","O                                           %","    #                                   O   @","  .                                        @ ","    x*=________________________________*O    "],["                   @%_--*x                   ","                 #         _                 ","                -        ~                   ","                          +                  ","                 _         0   X             ","            @   %           x   0            ","           O   O                 *           ","          %   @       oX          -          ","         _                                   ","        .                        -           ","          ~                       *          ","         +                         o   x     ","    X   0             O$            X   0    ","   0   X            @   O                +   ","  +                 o   %                 ~  "," ~                                      .    ","O                                           %","    #                                   O   @","  .                                        @ ","    x*=________________________________*O    "],["                   @%_--*x                   ","                 #         _                 ","                -        ~                   ","                          +                  ","                 _         0   X             ","            @   %           x   0            ","           O   O                 *           ","          %   @       oX          -          ","         _                                   ","        .                        -           ","          ~                       *          ","         +                         o   x     ","    X   0             O$            X   0    ","   0   X            @   O                +   ","  +                 o   %                 ~  "," ~                                      .    ","O                                           %","    #                                   O   @","  .                                        @ ","    x*=________________________________*O    "],["                   @%_--*x                   ","                 #         _                 ","                -        ~                   ","                          +                  ","                 _         0   X             ","            @   %           x   0            ","           O   O                 *           ","          %   @       oX          -          ","         _                                   ","        .                        -           ","          ~                       *          ","         +                         o   x     ","    X   0             O$            X   0    ","   0   X            @   O                +   ","  +                 o   %                 ~  "," ~                                      .    ","O                                           %","    #                                   O   @","  .                                        @ ","    x*=________________________________*O    "],["                   @%_--*x                   ","                 #         _                 ","                -        ~                   ","                          +                  ","                 _         0   X             ","            @   %           x   0            ","           O   O                 *           ","          %   @       oX          -          ","         _                                   ","        .                        -           ","          ~                       *          ","         +                         o   x     ","    X   0             O$            X   0    ","   0   X            @   O                +   ","  +                 o   %                 ~  "," ~                                      .    ","O                                           %","    #                                   O   @","  .                                        @ ","    x*=________________________________*O    "],["                   @%_--*x                   ","                 #         _                 ","                -        ~                   ","                          +                  ","                 _         0   X             ","            @   %           x   0            ","           O   O                 *           ","          %   @       oX          -          ","         _                                   ","        .                        -           ","          ~                       *          ","         +                         o   x     ","    X   0             O$            X   0    ","   0   X            @   O                +   ","  +                 o   %                 ~  "," ~                                      .    ","O                                           %","    #                                   O   @","  .                                        @ ","    x*=________________________________*O    "],["                   @%_--*x                   ","                 #         _                 ","                -        ~                   ","                          +                  ","                 _         0   X             ","            @   %           x   0            ","           O   O                 *           ","          %   @       oX          -          ","         _                                   ","        .                        -           ","          ~                       *          ","         +                         o   x     ","    X   0             O$            X   0    ","   0   X            @   O                +   ","  +                 o   %                 ~  "," ~                                      .    ","O                                           %","    #                                   O   @","  .                                        @ ","    x*=________________________________*O    "],["                   @%_--*x                   ","                 #         _                 ","                -        ~                   ","                          +                  ","                 _         0   X             ","            @   %           x   0            ","           O   O                 *           ","          %   @       oX          -          ","         _                                   ","        .                        -           ","          ~                       *          ","         +                         o   x     ","    X   0             O$            X   0    ","   0   X            @   O                +   ","  +                 o   %                 ~  "," ~                                      .    ","O                                           %","    #                                   O   @","  .                                        @ ","    x*=________________________________*O    "],["                   @%_--*x                   ","                 #         _                 ","                -        ~                   ","                          +                  ","                 _         0   X             ","            @   %           x   0            ","           O   O                 *           ","          %   @       oX          -          ","         _                                   ","        .                        -           ","          ~                       *          ","         +                         o   x     ","    X   0             O$            X   0    ","   0   X            @   O                +   ","  +                 o   %                 ~  "," ~                                      .    ","O                                           %","    #                                   O   @","  .                                        @ ","    x*=________________________________*O    "],["                   @%_--*x                   ","                 #         _                 ","                -        ~                   ","                          +                  ","                 _         0   X             ","            @   %           x   0            ","           O   O                 *           ","          %   @       oX          -          ","         _                                   ","        .                        -           ","          ~                       *          ","         +                         o   x     ","    X   0             O$            X   0    ","   0   X            @   O                +   ","  +                 o   %                 ~  "," ~                                      .    ","O                                           %","    #                                   O   @","  .                                        @ ","    x*=________________________________*O    "],["                   @%_--*x                   ","                 #         _                 ","                -        ~                   ","                          +                  ","                 _         0   X             ","            @   %           x   0            ","           O   O                 *           ","          %   @       oX          -          ","         _                                   ","        .                        -           ","          ~                       *          ","         +                         o   x     ","    X   0             O$            X   0    ","   0   X            @   O                +   ","  +                 o   %                 ~  "," ~                                      .    ","O                                           %","    #                                   O   @","  .                                        @ ","    x*=________________________________*O    "],["                   @%_--*x                   ","                 #         _                 ","                -        ~                   ","                          +                  ","                 _         0   X             ","            @   %           x   0            ","           O   O                 *           ","          %   @       oX          -          ","         _                                   ","        .                        -           ","          ~                       *          ","         +                         o   x     ","    X   0             O$            X   0    ","   0   X            @   O                +   ","  +                 o   %                 ~  "," ~                                      .    ","O                                           %","    #                                   O   @","  .                                        @ ","    x*=________________________________*O    "],["                   @%_--*x                   ","                 #         _                 ","                -        ~                   ","                          +                  ","                 _         0   X             ","            @   %           x   0            ","           O   O                 *           ","          %   @       oX          -          ","         _                                   ","        .                        -           ","          ~                       *          ","         +                         o   x     ","    X   0             O$            X   0    ","   0   X            @   O                +   ","  +                 o   %                 ~  "," ~                                      .    ","O                                           %","    #                                   O   @","  .                                        @ ","    x*=________________________________*O    "],["                   @%_--*x                   ","                 #         _                 ","                -        ~                   ","                          +                  ","                 _         0   X             ","            @   %           x   0            ","           O   O                 *           ","          %   @       oX          -          ","         _                                   ","        .                        -           ","          ~                       *          ","         +                         o   x     ","    X   0             O$            X   0    ","   0   X            @   O                +   ","  +                 o   %                 ~  "," ~                                      .    ","O                                           %","    #                                   O   @","  .                                        @ ","    x*=________________________________*O    "]]}